sheet_stream/__init__.py
sheet_stream/erros/__init__.py
sheet_stream/sheets/__init__.py
sheet_stream/sheets/load.py
sheet_stream/sheets/save.py
sheet_stream/text/__init__.py
sheet_stream/text/date.py
sheet_stream/type_utils/__init__.py
sheet_stream/type_utils/enums.py
sheet_stream/type_utils/list.py
sheet_stream/type_utils/metadata_file.py
sheet_stream/type_utils/table.py
sheet_stream/utils/__init__.py
sheet_stream-0.1.3.dist-info/METADATA
sheet_stream-0.1.3.dist-info/WHEEL
sheet_stream-0.1.3.dist-info/top_level.txt
sheet_stream-0.1.3.dist-info/RECORD
