Metadata-Version: 2.4
Name: sheet_stream
Version: 0.1.3
Summary: Leitura de dados em planilhas .csv/.ods/.xlsx
Author: Bruno Chaves
Requires-Python: >=3.11
Requires-Dist: soup_files>=1.4.1
Requires-Dist: scipy
Requires-Dist: openpyxl
Requires-Dist: odfpy
Requires-Dist: pandas
Requires-Dist: requests>=2.32.4
